project_system/__init__.py
project_system/__meta__.py
project_system/tests.py
project_system-0.2.5.data/scripts/project-clone
project_system-0.2.5.data/scripts/project-completion-init
project_system-0.2.5.data/scripts/project-conf-init
project_system-0.2.5.data/scripts/project-git-init
project_system-0.2.5.data/scripts/project-list
project_system-0.2.5.data/scripts/project-new
project_system-0.2.5.data/scripts/project-open
project_system-0.2.5.data/scripts/project-rebuild
project_system-0.2.5.data/scripts/project-workon
project_system-0.2.5.dist-info/METADATA
project_system-0.2.5.dist-info/WHEEL
project_system-0.2.5.dist-info/top_level.txt
project_system-0.2.5.dist-info/RECORD
