Metadata-Version: 1.0
Name: project-system
Version: 0.2.5
Summary: create and open projects
Home-page: http://project-system.readthedocs.io
Author: Ian Dennis Miller
Author-email: iandennismiller@gmail.com
License: MIT
Platform: UNKNOWN
